[
{
    "arguments": [
        "clang",
        "-Wno-documentation-unknown-command",
        "-Wno-unknown-warning-option",
        "-Wno-unknown-pragmas",
        "-nostdinc",
        "-nostdinc++",
        "-DQT_QML_DEBUG",
        "-g",
        "-std=gnu++17",
        "-fsyntax-only",
        "-m64",
        "--target=x86_64-w64-mingw32",
        "-DMINGW_HAS_SECURE_API",
        "-DQT_CORE_LIB",
        "-DQT_GUI_LIB",
        "-DQT_NEEDS_QMAIN",
        "-DQT_NETWORK_LIB",
        "-DQT_WIDGETS_LIB",
        "-DUNICODE",
        "-DWIN32",
        "-DWIN64",
        "-D_ENABLE_EXTENDED_ALIGNED_STORAGE",
        "-D_UNICODE",
        "-D_WIN64",
        "-DQ_CREATOR_RUN",
        "-I",
        "D:\\Qt\\Tools\\QtCreator\\share\\qtcreator\\cplusplus\\wrappedMingwHeaders",
        "-I",
        "D:\\Qt\\Tools\\QtCreator\\share\\qtcreator\\cplusplus\\wrappedQtHeaders",
        "-I",
        "D:\\Qt\\Tools\\QtCreator\\share\\qtcreator\\cplusplus\\wrappedQtHeaders\\QtCore",
        "-I",
        "C:\\Users\\103so\\Desktop\\Time Comtrollerr\\build-Client-Desktop_Qt_6_3_1_MinGW_64_bit-Debug",
        "-I",
        "C:\\Users\\103so\\Desktop\\Time Comtrollerr\\Client",
        "-I",
        "C:\\Users\\103so\\Desktop\\Time Comtrollerr\\build-Client-Desktop_Qt_6_3_1_MinGW_64_bit-Debug\\Client_autogen\\include",
        "-I",
        "D:\\Qt\\6.3.1\\mingw_64\\include\\QtCore",
        "-I",
        "D:\\Qt\\6.3.1\\mingw_64\\include",
        "-I",
        "D:\\Qt\\6.3.1\\mingw_64\\mkspecs\\win32-g++",
        "-I",
        "D:\\Qt\\6.3.1\\mingw_64\\include\\QtWidgets",
        "-I",
        "D:\\Qt\\6.3.1\\mingw_64\\include\\QtGui",
        "-I",
        "D:\\Qt\\6.3.1\\mingw_64\\include\\QtNetwork",
        "-isystem",
        "D:\\Qt\\Tools\\mingw1120_64\\lib\\gcc\\x86_64-w64-mingw32\\11.2.0\\include\\c++",
        "-isystem",
        "D:\\Qt\\Tools\\mingw1120_64\\lib\\gcc\\x86_64-w64-mingw32\\11.2.0\\include\\c++\\x86_64-w64-mingw32",
        "-isystem",
        "D:\\Qt\\Tools\\mingw1120_64\\lib\\gcc\\x86_64-w64-mingw32\\11.2.0\\include\\c++\\backward",
        "-isystem",
        "D:\\Qt\\Tools\\QtCreator\\bin\\clang\\lib\\clang\\14.0.3\\include",
        "-isystem",
        "D:\\Qt\\Tools\\mingw1120_64\\x86_64-w64-mingw32\\include",
        "-fmessage-length=0",
        "-fdiagnostics-show-note-include-stack",
        "-fretain-comments-from-system-headers",
        "-fmacro-backtrace-limit=0",
        "-ferror-limit=1000",
        "-x",
        "c++",
        "C:\\Users\\103so\\Desktop\\Time Comtrollerr\\Client\\main.cpp"
    ],
    "directory": "C:/Users/103so/Desktop/Time Comtrollerr/build-Client-Desktop_Qt_6_3_1_MinGW_64_bit-Debug/.qtc_clangd",
    "file": "C:/Users/103so/Desktop/Time Comtrollerr/Client/main.cpp"
},
{
    "arguments": [
        "clang",
        "-Wno-documentation-unknown-command",
        "-Wno-unknown-warning-option",
        "-Wno-unknown-pragmas",
        "-nostdinc",
        "-nostdinc++",
        "-DQT_QML_DEBUG",
        "-g",
        "-std=gnu++17",
        "-fsyntax-only",
        "-m64",
        "--target=x86_64-w64-mingw32",
        "-DMINGW_HAS_SECURE_API",
        "-DQT_CORE_LIB",
        "-DQT_GUI_LIB",
        "-DQT_NEEDS_QMAIN",
        "-DQT_NETWORK_LIB",
        "-DQT_WIDGETS_LIB",
        "-DUNICODE",
        "-DWIN32",
        "-DWIN64",
        "-D_ENABLE_EXTENDED_ALIGNED_STORAGE",
        "-D_UNICODE",
        "-D_WIN64",
        "-DQ_CREATOR_RUN",
        "-I",
        "D:\\Qt\\Tools\\QtCreator\\share\\qtcreator\\cplusplus\\wrappedMingwHeaders",
        "-I",
        "D:\\Qt\\Tools\\QtCreator\\share\\qtcreator\\cplusplus\\wrappedQtHeaders",
        "-I",
        "D:\\Qt\\Tools\\QtCreator\\share\\qtcreator\\cplusplus\\wrappedQtHeaders\\QtCore",
        "-I",
        "C:\\Users\\103so\\Desktop\\Time Comtrollerr\\build-Client-Desktop_Qt_6_3_1_MinGW_64_bit-Debug",
        "-I",
        "C:\\Users\\103so\\Desktop\\Time Comtrollerr\\Client",
        "-I",
        "C:\\Users\\103so\\Desktop\\Time Comtrollerr\\build-Client-Desktop_Qt_6_3_1_MinGW_64_bit-Debug\\Client_autogen\\include",
        "-I",
        "D:\\Qt\\6.3.1\\mingw_64\\include\\QtCore",
        "-I",
        "D:\\Qt\\6.3.1\\mingw_64\\include",
        "-I",
        "D:\\Qt\\6.3.1\\mingw_64\\mkspecs\\win32-g++",
        "-I",
        "D:\\Qt\\6.3.1\\mingw_64\\include\\QtWidgets",
        "-I",
        "D:\\Qt\\6.3.1\\mingw_64\\include\\QtGui",
        "-I",
        "D:\\Qt\\6.3.1\\mingw_64\\include\\QtNetwork",
        "-isystem",
        "D:\\Qt\\Tools\\mingw1120_64\\lib\\gcc\\x86_64-w64-mingw32\\11.2.0\\include\\c++",
        "-isystem",
        "D:\\Qt\\Tools\\mingw1120_64\\lib\\gcc\\x86_64-w64-mingw32\\11.2.0\\include\\c++\\x86_64-w64-mingw32",
        "-isystem",
        "D:\\Qt\\Tools\\mingw1120_64\\lib\\gcc\\x86_64-w64-mingw32\\11.2.0\\include\\c++\\backward",
        "-isystem",
        "D:\\Qt\\Tools\\QtCreator\\bin\\clang\\lib\\clang\\14.0.3\\include",
        "-isystem",
        "D:\\Qt\\Tools\\mingw1120_64\\x86_64-w64-mingw32\\include",
        "-fmessage-length=0",
        "-fdiagnostics-show-note-include-stack",
        "-fretain-comments-from-system-headers",
        "-fmacro-backtrace-limit=0",
        "-ferror-limit=1000",
        "-x",
        "c++",
        "C:\\Users\\103so\\Desktop\\Time Comtrollerr\\Client\\mainwindow.cpp"
    ],
    "directory": "C:/Users/103so/Desktop/Time Comtrollerr/build-Client-Desktop_Qt_6_3_1_MinGW_64_bit-Debug/.qtc_clangd",
    "file": "C:/Users/103so/Desktop/Time Comtrollerr/Client/mainwindow.cpp"
},
{
    "arguments": [
        "clang",
        "-Wno-documentation-unknown-command",
        "-Wno-unknown-warning-option",
        "-Wno-unknown-pragmas",
        "-nostdinc",
        "-nostdinc++",
        "-DQT_QML_DEBUG",
        "-g",
        "-std=gnu++17",
        "-fsyntax-only",
        "-m64",
        "--target=x86_64-w64-mingw32",
        "-DMINGW_HAS_SECURE_API",
        "-DQT_CORE_LIB",
        "-DQT_GUI_LIB",
        "-DQT_NEEDS_QMAIN",
        "-DQT_NETWORK_LIB",
        "-DQT_WIDGETS_LIB",
        "-DUNICODE",
        "-DWIN32",
        "-DWIN64",
        "-D_ENABLE_EXTENDED_ALIGNED_STORAGE",
        "-D_UNICODE",
        "-D_WIN64",
        "-DQ_CREATOR_RUN",
        "-I",
        "D:\\Qt\\Tools\\QtCreator\\share\\qtcreator\\cplusplus\\wrappedMingwHeaders",
        "-I",
        "D:\\Qt\\Tools\\QtCreator\\share\\qtcreator\\cplusplus\\wrappedQtHeaders",
        "-I",
        "D:\\Qt\\Tools\\QtCreator\\share\\qtcreator\\cplusplus\\wrappedQtHeaders\\QtCore",
        "-I",
        "C:\\Users\\103so\\Desktop\\Time Comtrollerr\\build-Client-Desktop_Qt_6_3_1_MinGW_64_bit-Debug",
        "-I",
        "C:\\Users\\103so\\Desktop\\Time Comtrollerr\\Client",
        "-I",
        "C:\\Users\\103so\\Desktop\\Time Comtrollerr\\build-Client-Desktop_Qt_6_3_1_MinGW_64_bit-Debug\\Client_autogen\\include",
        "-I",
        "D:\\Qt\\6.3.1\\mingw_64\\include\\QtCore",
        "-I",
        "D:\\Qt\\6.3.1\\mingw_64\\include",
        "-I",
        "D:\\Qt\\6.3.1\\mingw_64\\mkspecs\\win32-g++",
        "-I",
        "D:\\Qt\\6.3.1\\mingw_64\\include\\QtWidgets",
        "-I",
        "D:\\Qt\\6.3.1\\mingw_64\\include\\QtGui",
        "-I",
        "D:\\Qt\\6.3.1\\mingw_64\\include\\QtNetwork",
        "-isystem",
        "D:\\Qt\\Tools\\mingw1120_64\\lib\\gcc\\x86_64-w64-mingw32\\11.2.0\\include\\c++",
        "-isystem",
        "D:\\Qt\\Tools\\mingw1120_64\\lib\\gcc\\x86_64-w64-mingw32\\11.2.0\\include\\c++\\x86_64-w64-mingw32",
        "-isystem",
        "D:\\Qt\\Tools\\mingw1120_64\\lib\\gcc\\x86_64-w64-mingw32\\11.2.0\\include\\c++\\backward",
        "-isystem",
        "D:\\Qt\\Tools\\QtCreator\\bin\\clang\\lib\\clang\\14.0.3\\include",
        "-isystem",
        "D:\\Qt\\Tools\\mingw1120_64\\x86_64-w64-mingw32\\include",
        "-fmessage-length=0",
        "-fdiagnostics-show-note-include-stack",
        "-fretain-comments-from-system-headers",
        "-fmacro-backtrace-limit=0",
        "-ferror-limit=1000",
        "-x",
        "c++",
        "C:\\Users\\103so\\Desktop\\Time Comtrollerr\\Client\\secondwindow.cpp"
    ],
    "directory": "C:/Users/103so/Desktop/Time Comtrollerr/build-Client-Desktop_Qt_6_3_1_MinGW_64_bit-Debug/.qtc_clangd",
    "file": "C:/Users/103so/Desktop/Time Comtrollerr/Client/secondwindow.cpp"
},
{
    "arguments": [
        "clang",
        "-Wno-documentation-unknown-command",
        "-Wno-unknown-warning-option",
        "-Wno-unknown-pragmas",
        "-nostdinc",
        "-nostdinc++",
        "-DQT_QML_DEBUG",
        "-g",
        "-std=gnu++17",
        "-fsyntax-only",
        "-m64",
        "--target=x86_64-w64-mingw32",
        "-DMINGW_HAS_SECURE_API",
        "-DQT_CORE_LIB",
        "-DQT_GUI_LIB",
        "-DQT_NEEDS_QMAIN",
        "-DQT_NETWORK_LIB",
        "-DQT_WIDGETS_LIB",
        "-DUNICODE",
        "-DWIN32",
        "-DWIN64",
        "-D_ENABLE_EXTENDED_ALIGNED_STORAGE",
        "-D_UNICODE",
        "-D_WIN64",
        "-DQ_CREATOR_RUN",
        "-I",
        "D:\\Qt\\Tools\\QtCreator\\share\\qtcreator\\cplusplus\\wrappedMingwHeaders",
        "-I",
        "D:\\Qt\\Tools\\QtCreator\\share\\qtcreator\\cplusplus\\wrappedQtHeaders",
        "-I",
        "D:\\Qt\\Tools\\QtCreator\\share\\qtcreator\\cplusplus\\wrappedQtHeaders\\QtCore",
        "-I",
        "C:\\Users\\103so\\Desktop\\Time Comtrollerr\\build-Client-Desktop_Qt_6_3_1_MinGW_64_bit-Debug",
        "-I",
        "C:\\Users\\103so\\Desktop\\Time Comtrollerr\\Client",
        "-I",
        "C:\\Users\\103so\\Desktop\\Time Comtrollerr\\build-Client-Desktop_Qt_6_3_1_MinGW_64_bit-Debug\\Client_autogen\\include",
        "-I",
        "D:\\Qt\\6.3.1\\mingw_64\\include\\QtCore",
        "-I",
        "D:\\Qt\\6.3.1\\mingw_64\\include",
        "-I",
        "D:\\Qt\\6.3.1\\mingw_64\\mkspecs\\win32-g++",
        "-I",
        "D:\\Qt\\6.3.1\\mingw_64\\include\\QtWidgets",
        "-I",
        "D:\\Qt\\6.3.1\\mingw_64\\include\\QtGui",
        "-I",
        "D:\\Qt\\6.3.1\\mingw_64\\include\\QtNetwork",
        "-isystem",
        "D:\\Qt\\Tools\\mingw1120_64\\lib\\gcc\\x86_64-w64-mingw32\\11.2.0\\include\\c++",
        "-isystem",
        "D:\\Qt\\Tools\\mingw1120_64\\lib\\gcc\\x86_64-w64-mingw32\\11.2.0\\include\\c++\\x86_64-w64-mingw32",
        "-isystem",
        "D:\\Qt\\Tools\\mingw1120_64\\lib\\gcc\\x86_64-w64-mingw32\\11.2.0\\include\\c++\\backward",
        "-isystem",
        "D:\\Qt\\Tools\\QtCreator\\bin\\clang\\lib\\clang\\14.0.3\\include",
        "-isystem",
        "D:\\Qt\\Tools\\mingw1120_64\\x86_64-w64-mingw32\\include",
        "-fmessage-length=0",
        "-fdiagnostics-show-note-include-stack",
        "-fretain-comments-from-system-headers",
        "-fmacro-backtrace-limit=0",
        "-ferror-limit=1000",
        "-x",
        "c++",
        "C:\\Users\\103so\\Desktop\\Time Comtrollerr\\Client\\client.cpp"
    ],
    "directory": "C:/Users/103so/Desktop/Time Comtrollerr/build-Client-Desktop_Qt_6_3_1_MinGW_64_bit-Debug/.qtc_clangd",
    "file": "C:/Users/103so/Desktop/Time Comtrollerr/Client/client.cpp"
},
{
    "arguments": [
        "clang",
        "-Wno-documentation-unknown-command",
        "-Wno-unknown-warning-option",
        "-Wno-unknown-pragmas",
        "-nostdinc",
        "-nostdinc++",
        "-DQT_QML_DEBUG",
        "-g",
        "-std=gnu++17",
        "-fsyntax-only",
        "-m64",
        "--target=x86_64-w64-mingw32",
        "-DMINGW_HAS_SECURE_API",
        "-DQT_CORE_LIB",
        "-DQT_GUI_LIB",
        "-DQT_NEEDS_QMAIN",
        "-DQT_NETWORK_LIB",
        "-DQT_WIDGETS_LIB",
        "-DUNICODE",
        "-DWIN32",
        "-DWIN64",
        "-D_ENABLE_EXTENDED_ALIGNED_STORAGE",
        "-D_UNICODE",
        "-D_WIN64",
        "-DQ_CREATOR_RUN",
        "-I",
        "D:\\Qt\\Tools\\QtCreator\\share\\qtcreator\\cplusplus\\wrappedMingwHeaders",
        "-I",
        "D:\\Qt\\Tools\\QtCreator\\share\\qtcreator\\cplusplus\\wrappedQtHeaders",
        "-I",
        "D:\\Qt\\Tools\\QtCreator\\share\\qtcreator\\cplusplus\\wrappedQtHeaders\\QtCore",
        "-I",
        "C:\\Users\\103so\\Desktop\\Time Comtrollerr\\build-Client-Desktop_Qt_6_3_1_MinGW_64_bit-Debug",
        "-I",
        "C:\\Users\\103so\\Desktop\\Time Comtrollerr\\Client",
        "-I",
        "C:\\Users\\103so\\Desktop\\Time Comtrollerr\\build-Client-Desktop_Qt_6_3_1_MinGW_64_bit-Debug\\Client_autogen\\include",
        "-I",
        "D:\\Qt\\6.3.1\\mingw_64\\include\\QtCore",
        "-I",
        "D:\\Qt\\6.3.1\\mingw_64\\include",
        "-I",
        "D:\\Qt\\6.3.1\\mingw_64\\mkspecs\\win32-g++",
        "-I",
        "D:\\Qt\\6.3.1\\mingw_64\\include\\QtWidgets",
        "-I",
        "D:\\Qt\\6.3.1\\mingw_64\\include\\QtGui",
        "-I",
        "D:\\Qt\\6.3.1\\mingw_64\\include\\QtNetwork",
        "-isystem",
        "D:\\Qt\\Tools\\mingw1120_64\\lib\\gcc\\x86_64-w64-mingw32\\11.2.0\\include\\c++",
        "-isystem",
        "D:\\Qt\\Tools\\mingw1120_64\\lib\\gcc\\x86_64-w64-mingw32\\11.2.0\\include\\c++\\x86_64-w64-mingw32",
        "-isystem",
        "D:\\Qt\\Tools\\mingw1120_64\\lib\\gcc\\x86_64-w64-mingw32\\11.2.0\\include\\c++\\backward",
        "-isystem",
        "D:\\Qt\\Tools\\QtCreator\\bin\\clang\\lib\\clang\\14.0.3\\include",
        "-isystem",
        "D:\\Qt\\Tools\\mingw1120_64\\x86_64-w64-mingw32\\include",
        "-fmessage-length=0",
        "-fdiagnostics-show-note-include-stack",
        "-fretain-comments-from-system-headers",
        "-fmacro-backtrace-limit=0",
        "-ferror-limit=1000",
        "-x",
        "c++",
        "C:\\Users\\103so\\Desktop\\Time Comtrollerr\\Client\\windowssystem.cpp"
    ],
    "directory": "C:/Users/103so/Desktop/Time Comtrollerr/build-Client-Desktop_Qt_6_3_1_MinGW_64_bit-Debug/.qtc_clangd",
    "file": "C:/Users/103so/Desktop/Time Comtrollerr/Client/windowssystem.cpp"
},
{
    "arguments": [
        "clang",
        "-Wno-documentation-unknown-command",
        "-Wno-unknown-warning-option",
        "-Wno-unknown-pragmas",
        "-nostdinc",
        "-nostdinc++",
        "-DQT_QML_DEBUG",
        "-g",
        "-std=gnu++17",
        "-fsyntax-only",
        "-m64",
        "--target=x86_64-w64-mingw32",
        "-DMINGW_HAS_SECURE_API",
        "-DQT_CORE_LIB",
        "-DQT_GUI_LIB",
        "-DQT_NEEDS_QMAIN",
        "-DQT_NETWORK_LIB",
        "-DQT_WIDGETS_LIB",
        "-DUNICODE",
        "-DWIN32",
        "-DWIN64",
        "-D_ENABLE_EXTENDED_ALIGNED_STORAGE",
        "-D_UNICODE",
        "-D_WIN64",
        "-DQ_CREATOR_RUN",
        "-I",
        "D:\\Qt\\Tools\\QtCreator\\share\\qtcreator\\cplusplus\\wrappedMingwHeaders",
        "-I",
        "D:\\Qt\\Tools\\QtCreator\\share\\qtcreator\\cplusplus\\wrappedQtHeaders",
        "-I",
        "D:\\Qt\\Tools\\QtCreator\\share\\qtcreator\\cplusplus\\wrappedQtHeaders\\QtCore",
        "-I",
        "C:\\Users\\103so\\Desktop\\Time Comtrollerr\\build-Client-Desktop_Qt_6_3_1_MinGW_64_bit-Debug",
        "-I",
        "C:\\Users\\103so\\Desktop\\Time Comtrollerr\\Client",
        "-I",
        "C:\\Users\\103so\\Desktop\\Time Comtrollerr\\build-Client-Desktop_Qt_6_3_1_MinGW_64_bit-Debug\\Client_autogen\\include",
        "-I",
        "D:\\Qt\\6.3.1\\mingw_64\\include\\QtCore",
        "-I",
        "D:\\Qt\\6.3.1\\mingw_64\\include",
        "-I",
        "D:\\Qt\\6.3.1\\mingw_64\\mkspecs\\win32-g++",
        "-I",
        "D:\\Qt\\6.3.1\\mingw_64\\include\\QtWidgets",
        "-I",
        "D:\\Qt\\6.3.1\\mingw_64\\include\\QtGui",
        "-I",
        "D:\\Qt\\6.3.1\\mingw_64\\include\\QtNetwork",
        "-isystem",
        "D:\\Qt\\Tools\\mingw1120_64\\lib\\gcc\\x86_64-w64-mingw32\\11.2.0\\include\\c++",
        "-isystem",
        "D:\\Qt\\Tools\\mingw1120_64\\lib\\gcc\\x86_64-w64-mingw32\\11.2.0\\include\\c++\\x86_64-w64-mingw32",
        "-isystem",
        "D:\\Qt\\Tools\\mingw1120_64\\lib\\gcc\\x86_64-w64-mingw32\\11.2.0\\include\\c++\\backward",
        "-isystem",
        "D:\\Qt\\Tools\\QtCreator\\bin\\clang\\lib\\clang\\14.0.3\\include",
        "-isystem",
        "D:\\Qt\\Tools\\mingw1120_64\\x86_64-w64-mingw32\\include",
        "-fmessage-length=0",
        "-fdiagnostics-show-note-include-stack",
        "-fretain-comments-from-system-headers",
        "-fmacro-backtrace-limit=0",
        "-ferror-limit=1000",
        "-x",
        "c++",
        "C:\\Users\\103so\\Desktop\\Time Comtrollerr\\Client\\operatingsystemprogram.cpp"
    ],
    "directory": "C:/Users/103so/Desktop/Time Comtrollerr/build-Client-Desktop_Qt_6_3_1_MinGW_64_bit-Debug/.qtc_clangd",
    "file": "C:/Users/103so/Desktop/Time Comtrollerr/Client/operatingsystemprogram.cpp"
},
{
    "arguments": [
        "clang",
        "-Wno-documentation-unknown-command",
        "-Wno-unknown-warning-option",
        "-Wno-unknown-pragmas",
        "-nostdinc",
        "-nostdinc++",
        "-DQT_QML_DEBUG",
        "-g",
        "-std=gnu++17",
        "-fsyntax-only",
        "-m64",
        "--target=x86_64-w64-mingw32",
        "-DMINGW_HAS_SECURE_API",
        "-DQT_CORE_LIB",
        "-DQT_GUI_LIB",
        "-DQT_NEEDS_QMAIN",
        "-DQT_NETWORK_LIB",
        "-DQT_WIDGETS_LIB",
        "-DUNICODE",
        "-DWIN32",
        "-DWIN64",
        "-D_ENABLE_EXTENDED_ALIGNED_STORAGE",
        "-D_UNICODE",
        "-D_WIN64",
        "-DQ_CREATOR_RUN",
        "-I",
        "D:\\Qt\\Tools\\QtCreator\\share\\qtcreator\\cplusplus\\wrappedMingwHeaders",
        "-I",
        "D:\\Qt\\Tools\\QtCreator\\share\\qtcreator\\cplusplus\\wrappedQtHeaders",
        "-I",
        "D:\\Qt\\Tools\\QtCreator\\share\\qtcreator\\cplusplus\\wrappedQtHeaders\\QtCore",
        "-I",
        "C:\\Users\\103so\\Desktop\\Time Comtrollerr\\build-Client-Desktop_Qt_6_3_1_MinGW_64_bit-Debug",
        "-I",
        "C:\\Users\\103so\\Desktop\\Time Comtrollerr\\Client",
        "-I",
        "C:\\Users\\103so\\Desktop\\Time Comtrollerr\\build-Client-Desktop_Qt_6_3_1_MinGW_64_bit-Debug\\Client_autogen\\include",
        "-I",
        "D:\\Qt\\6.3.1\\mingw_64\\include\\QtCore",
        "-I",
        "D:\\Qt\\6.3.1\\mingw_64\\include",
        "-I",
        "D:\\Qt\\6.3.1\\mingw_64\\mkspecs\\win32-g++",
        "-I",
        "D:\\Qt\\6.3.1\\mingw_64\\include\\QtWidgets",
        "-I",
        "D:\\Qt\\6.3.1\\mingw_64\\include\\QtGui",
        "-I",
        "D:\\Qt\\6.3.1\\mingw_64\\include\\QtNetwork",
        "-isystem",
        "D:\\Qt\\Tools\\mingw1120_64\\lib\\gcc\\x86_64-w64-mingw32\\11.2.0\\include\\c++",
        "-isystem",
        "D:\\Qt\\Tools\\mingw1120_64\\lib\\gcc\\x86_64-w64-mingw32\\11.2.0\\include\\c++\\x86_64-w64-mingw32",
        "-isystem",
        "D:\\Qt\\Tools\\mingw1120_64\\lib\\gcc\\x86_64-w64-mingw32\\11.2.0\\include\\c++\\backward",
        "-isystem",
        "D:\\Qt\\Tools\\QtCreator\\bin\\clang\\lib\\clang\\14.0.3\\include",
        "-isystem",
        "D:\\Qt\\Tools\\mingw1120_64\\x86_64-w64-mingw32\\include",
        "-fmessage-length=0",
        "-fdiagnostics-show-note-include-stack",
        "-fretain-comments-from-system-headers",
        "-fmacro-backtrace-limit=0",
        "-ferror-limit=1000",
        "-x",
        "c++",
        "C:\\Users\\103so\\Desktop\\Time Comtrollerr\\Client\\windowssystemprogram.cpp"
    ],
    "directory": "C:/Users/103so/Desktop/Time Comtrollerr/build-Client-Desktop_Qt_6_3_1_MinGW_64_bit-Debug/.qtc_clangd",
    "file": "C:/Users/103so/Desktop/Time Comtrollerr/Client/windowssystemprogram.cpp"
},
{
    "arguments": [
        "clang",
        "-Wno-documentation-unknown-command",
        "-Wno-unknown-warning-option",
        "-Wno-unknown-pragmas",
        "-nostdinc",
        "-nostdinc++",
        "-DQT_QML_DEBUG",
        "-g",
        "-std=gnu++17",
        "-fsyntax-only",
        "-m64",
        "--target=x86_64-w64-mingw32",
        "-DMINGW_HAS_SECURE_API",
        "-DQT_CORE_LIB",
        "-DQT_GUI_LIB",
        "-DQT_NEEDS_QMAIN",
        "-DQT_NETWORK_LIB",
        "-DQT_WIDGETS_LIB",
        "-DUNICODE",
        "-DWIN32",
        "-DWIN64",
        "-D_ENABLE_EXTENDED_ALIGNED_STORAGE",
        "-D_UNICODE",
        "-D_WIN64",
        "-DQ_CREATOR_RUN",
        "-I",
        "D:\\Qt\\Tools\\QtCreator\\share\\qtcreator\\cplusplus\\wrappedMingwHeaders",
        "-I",
        "D:\\Qt\\Tools\\QtCreator\\share\\qtcreator\\cplusplus\\wrappedQtHeaders",
        "-I",
        "D:\\Qt\\Tools\\QtCreator\\share\\qtcreator\\cplusplus\\wrappedQtHeaders\\QtCore",
        "-I",
        "C:\\Users\\103so\\Desktop\\Time Comtrollerr\\build-Client-Desktop_Qt_6_3_1_MinGW_64_bit-Debug",
        "-I",
        "C:\\Users\\103so\\Desktop\\Time Comtrollerr\\Client",
        "-I",
        "C:\\Users\\103so\\Desktop\\Time Comtrollerr\\build-Client-Desktop_Qt_6_3_1_MinGW_64_bit-Debug\\Client_autogen\\include",
        "-I",
        "D:\\Qt\\6.3.1\\mingw_64\\include\\QtCore",
        "-I",
        "D:\\Qt\\6.3.1\\mingw_64\\include",
        "-I",
        "D:\\Qt\\6.3.1\\mingw_64\\mkspecs\\win32-g++",
        "-I",
        "D:\\Qt\\6.3.1\\mingw_64\\include\\QtWidgets",
        "-I",
        "D:\\Qt\\6.3.1\\mingw_64\\include\\QtGui",
        "-I",
        "D:\\Qt\\6.3.1\\mingw_64\\include\\QtNetwork",
        "-isystem",
        "D:\\Qt\\Tools\\mingw1120_64\\lib\\gcc\\x86_64-w64-mingw32\\11.2.0\\include\\c++",
        "-isystem",
        "D:\\Qt\\Tools\\mingw1120_64\\lib\\gcc\\x86_64-w64-mingw32\\11.2.0\\include\\c++\\x86_64-w64-mingw32",
        "-isystem",
        "D:\\Qt\\Tools\\mingw1120_64\\lib\\gcc\\x86_64-w64-mingw32\\11.2.0\\include\\c++\\backward",
        "-isystem",
        "D:\\Qt\\Tools\\QtCreator\\bin\\clang\\lib\\clang\\14.0.3\\include",
        "-isystem",
        "D:\\Qt\\Tools\\mingw1120_64\\x86_64-w64-mingw32\\include",
        "-fmessage-length=0",
        "-fdiagnostics-show-note-include-stack",
        "-fretain-comments-from-system-headers",
        "-fmacro-backtrace-limit=0",
        "-ferror-limit=1000",
        "-x",
        "c++",
        "C:\\Users\\103so\\Desktop\\Time Comtrollerr\\Client\\activitytime.cpp"
    ],
    "directory": "C:/Users/103so/Desktop/Time Comtrollerr/build-Client-Desktop_Qt_6_3_1_MinGW_64_bit-Debug/.qtc_clangd",
    "file": "C:/Users/103so/Desktop/Time Comtrollerr/Client/activitytime.cpp"
},
{
    "arguments": [
        "clang",
        "-Wno-documentation-unknown-command",
        "-Wno-unknown-warning-option",
        "-Wno-unknown-pragmas",
        "-nostdinc",
        "-nostdinc++",
        "-DQT_QML_DEBUG",
        "-g",
        "-std=gnu++17",
        "-fsyntax-only",
        "-m64",
        "--target=x86_64-w64-mingw32",
        "-DMINGW_HAS_SECURE_API",
        "-DQT_CORE_LIB",
        "-DQT_GUI_LIB",
        "-DQT_NEEDS_QMAIN",
        "-DQT_NETWORK_LIB",
        "-DQT_WIDGETS_LIB",
        "-DUNICODE",
        "-DWIN32",
        "-DWIN64",
        "-D_ENABLE_EXTENDED_ALIGNED_STORAGE",
        "-D_UNICODE",
        "-D_WIN64",
        "-DQ_CREATOR_RUN",
        "-I",
        "D:\\Qt\\Tools\\QtCreator\\share\\qtcreator\\cplusplus\\wrappedMingwHeaders",
        "-I",
        "D:\\Qt\\Tools\\QtCreator\\share\\qtcreator\\cplusplus\\wrappedQtHeaders",
        "-I",
        "D:\\Qt\\Tools\\QtCreator\\share\\qtcreator\\cplusplus\\wrappedQtHeaders\\QtCore",
        "-I",
        "C:\\Users\\103so\\Desktop\\Time Comtrollerr\\build-Client-Desktop_Qt_6_3_1_MinGW_64_bit-Debug",
        "-I",
        "C:\\Users\\103so\\Desktop\\Time Comtrollerr\\Client",
        "-I",
        "C:\\Users\\103so\\Desktop\\Time Comtrollerr\\build-Client-Desktop_Qt_6_3_1_MinGW_64_bit-Debug\\Client_autogen\\include",
        "-I",
        "D:\\Qt\\6.3.1\\mingw_64\\include\\QtCore",
        "-I",
        "D:\\Qt\\6.3.1\\mingw_64\\include",
        "-I",
        "D:\\Qt\\6.3.1\\mingw_64\\mkspecs\\win32-g++",
        "-I",
        "D:\\Qt\\6.3.1\\mingw_64\\include\\QtWidgets",
        "-I",
        "D:\\Qt\\6.3.1\\mingw_64\\include\\QtGui",
        "-I",
        "D:\\Qt\\6.3.1\\mingw_64\\include\\QtNetwork",
        "-isystem",
        "D:\\Qt\\Tools\\mingw1120_64\\lib\\gcc\\x86_64-w64-mingw32\\11.2.0\\include\\c++",
        "-isystem",
        "D:\\Qt\\Tools\\mingw1120_64\\lib\\gcc\\x86_64-w64-mingw32\\11.2.0\\include\\c++\\x86_64-w64-mingw32",
        "-isystem",
        "D:\\Qt\\Tools\\mingw1120_64\\lib\\gcc\\x86_64-w64-mingw32\\11.2.0\\include\\c++\\backward",
        "-isystem",
        "D:\\Qt\\Tools\\QtCreator\\bin\\clang\\lib\\clang\\14.0.3\\include",
        "-isystem",
        "D:\\Qt\\Tools\\mingw1120_64\\x86_64-w64-mingw32\\include",
        "-fmessage-length=0",
        "-fdiagnostics-show-note-include-stack",
        "-fretain-comments-from-system-headers",
        "-fmacro-backtrace-limit=0",
        "-ferror-limit=1000",
        "-x",
        "c++",
        "C:\\Users\\103so\\Desktop\\Time Comtrollerr\\Client\\app.cpp"
    ],
    "directory": "C:/Users/103so/Desktop/Time Comtrollerr/build-Client-Desktop_Qt_6_3_1_MinGW_64_bit-Debug/.qtc_clangd",
    "file": "C:/Users/103so/Desktop/Time Comtrollerr/Client/app.cpp"
},
{
    "arguments": [
        "clang",
        "-Wno-documentation-unknown-command",
        "-Wno-unknown-warning-option",
        "-Wno-unknown-pragmas",
        "-nostdinc",
        "-nostdinc++",
        "-DQT_QML_DEBUG",
        "-g",
        "-std=gnu++17",
        "-fsyntax-only",
        "-m64",
        "--target=x86_64-w64-mingw32",
        "-DMINGW_HAS_SECURE_API",
        "-DQT_CORE_LIB",
        "-DQT_GUI_LIB",
        "-DQT_NEEDS_QMAIN",
        "-DQT_NETWORK_LIB",
        "-DQT_WIDGETS_LIB",
        "-DUNICODE",
        "-DWIN32",
        "-DWIN64",
        "-D_ENABLE_EXTENDED_ALIGNED_STORAGE",
        "-D_UNICODE",
        "-D_WIN64",
        "-DQ_CREATOR_RUN",
        "-I",
        "D:\\Qt\\Tools\\QtCreator\\share\\qtcreator\\cplusplus\\wrappedMingwHeaders",
        "-I",
        "D:\\Qt\\Tools\\QtCreator\\share\\qtcreator\\cplusplus\\wrappedQtHeaders",
        "-I",
        "D:\\Qt\\Tools\\QtCreator\\share\\qtcreator\\cplusplus\\wrappedQtHeaders\\QtCore",
        "-I",
        "C:\\Users\\103so\\Desktop\\Time Comtrollerr\\build-Client-Desktop_Qt_6_3_1_MinGW_64_bit-Debug",
        "-I",
        "C:\\Users\\103so\\Desktop\\Time Comtrollerr\\Client",
        "-I",
        "C:\\Users\\103so\\Desktop\\Time Comtrollerr\\build-Client-Desktop_Qt_6_3_1_MinGW_64_bit-Debug\\Client_autogen\\include",
        "-I",
        "D:\\Qt\\6.3.1\\mingw_64\\include\\QtCore",
        "-I",
        "D:\\Qt\\6.3.1\\mingw_64\\include",
        "-I",
        "D:\\Qt\\6.3.1\\mingw_64\\mkspecs\\win32-g++",
        "-I",
        "D:\\Qt\\6.3.1\\mingw_64\\include\\QtWidgets",
        "-I",
        "D:\\Qt\\6.3.1\\mingw_64\\include\\QtGui",
        "-I",
        "D:\\Qt\\6.3.1\\mingw_64\\include\\QtNetwork",
        "-isystem",
        "D:\\Qt\\Tools\\mingw1120_64\\lib\\gcc\\x86_64-w64-mingw32\\11.2.0\\include\\c++",
        "-isystem",
        "D:\\Qt\\Tools\\mingw1120_64\\lib\\gcc\\x86_64-w64-mingw32\\11.2.0\\include\\c++\\x86_64-w64-mingw32",
        "-isystem",
        "D:\\Qt\\Tools\\mingw1120_64\\lib\\gcc\\x86_64-w64-mingw32\\11.2.0\\include\\c++\\backward",
        "-isystem",
        "D:\\Qt\\Tools\\QtCreator\\bin\\clang\\lib\\clang\\14.0.3\\include",
        "-isystem",
        "D:\\Qt\\Tools\\mingw1120_64\\x86_64-w64-mingw32\\include",
        "-fmessage-length=0",
        "-fdiagnostics-show-note-include-stack",
        "-fretain-comments-from-system-headers",
        "-fmacro-backtrace-limit=0",
        "-ferror-limit=1000",
        "-x",
        "c++-header",
        "C:\\Users\\103so\\Desktop\\Time Comtrollerr\\Client\\mainwindow.h"
    ],
    "directory": "C:/Users/103so/Desktop/Time Comtrollerr/build-Client-Desktop_Qt_6_3_1_MinGW_64_bit-Debug/.qtc_clangd",
    "file": "C:/Users/103so/Desktop/Time Comtrollerr/Client/mainwindow.h"
},
{
    "arguments": [
        "clang",
        "-Wno-documentation-unknown-command",
        "-Wno-unknown-warning-option",
        "-Wno-unknown-pragmas",
        "-nostdinc",
        "-nostdinc++",
        "-DQT_QML_DEBUG",
        "-g",
        "-std=gnu++17",
        "-fsyntax-only",
        "-m64",
        "--target=x86_64-w64-mingw32",
        "-DMINGW_HAS_SECURE_API",
        "-DQT_CORE_LIB",
        "-DQT_GUI_LIB",
        "-DQT_NEEDS_QMAIN",
        "-DQT_NETWORK_LIB",
        "-DQT_WIDGETS_LIB",
        "-DUNICODE",
        "-DWIN32",
        "-DWIN64",
        "-D_ENABLE_EXTENDED_ALIGNED_STORAGE",
        "-D_UNICODE",
        "-D_WIN64",
        "-DQ_CREATOR_RUN",
        "-I",
        "D:\\Qt\\Tools\\QtCreator\\share\\qtcreator\\cplusplus\\wrappedMingwHeaders",
        "-I",
        "D:\\Qt\\Tools\\QtCreator\\share\\qtcreator\\cplusplus\\wrappedQtHeaders",
        "-I",
        "D:\\Qt\\Tools\\QtCreator\\share\\qtcreator\\cplusplus\\wrappedQtHeaders\\QtCore",
        "-I",
        "C:\\Users\\103so\\Desktop\\Time Comtrollerr\\build-Client-Desktop_Qt_6_3_1_MinGW_64_bit-Debug",
        "-I",
        "C:\\Users\\103so\\Desktop\\Time Comtrollerr\\Client",
        "-I",
        "C:\\Users\\103so\\Desktop\\Time Comtrollerr\\build-Client-Desktop_Qt_6_3_1_MinGW_64_bit-Debug\\Client_autogen\\include",
        "-I",
        "D:\\Qt\\6.3.1\\mingw_64\\include\\QtCore",
        "-I",
        "D:\\Qt\\6.3.1\\mingw_64\\include",
        "-I",
        "D:\\Qt\\6.3.1\\mingw_64\\mkspecs\\win32-g++",
        "-I",
        "D:\\Qt\\6.3.1\\mingw_64\\include\\QtWidgets",
        "-I",
        "D:\\Qt\\6.3.1\\mingw_64\\include\\QtGui",
        "-I",
        "D:\\Qt\\6.3.1\\mingw_64\\include\\QtNetwork",
        "-isystem",
        "D:\\Qt\\Tools\\mingw1120_64\\lib\\gcc\\x86_64-w64-mingw32\\11.2.0\\include\\c++",
        "-isystem",
        "D:\\Qt\\Tools\\mingw1120_64\\lib\\gcc\\x86_64-w64-mingw32\\11.2.0\\include\\c++\\x86_64-w64-mingw32",
        "-isystem",
        "D:\\Qt\\Tools\\mingw1120_64\\lib\\gcc\\x86_64-w64-mingw32\\11.2.0\\include\\c++\\backward",
        "-isystem",
        "D:\\Qt\\Tools\\QtCreator\\bin\\clang\\lib\\clang\\14.0.3\\include",
        "-isystem",
        "D:\\Qt\\Tools\\mingw1120_64\\x86_64-w64-mingw32\\include",
        "-fmessage-length=0",
        "-fdiagnostics-show-note-include-stack",
        "-fretain-comments-from-system-headers",
        "-fmacro-backtrace-limit=0",
        "-ferror-limit=1000",
        "-x",
        "c++-header",
        "C:\\Users\\103so\\Desktop\\Time Comtrollerr\\Client\\secondwindow.h"
    ],
    "directory": "C:/Users/103so/Desktop/Time Comtrollerr/build-Client-Desktop_Qt_6_3_1_MinGW_64_bit-Debug/.qtc_clangd",
    "file": "C:/Users/103so/Desktop/Time Comtrollerr/Client/secondwindow.h"
},
{
    "arguments": [
        "clang",
        "-Wno-documentation-unknown-command",
        "-Wno-unknown-warning-option",
        "-Wno-unknown-pragmas",
        "-nostdinc",
        "-nostdinc++",
        "-DQT_QML_DEBUG",
        "-g",
        "-std=gnu++17",
        "-fsyntax-only",
        "-m64",
        "--target=x86_64-w64-mingw32",
        "-DMINGW_HAS_SECURE_API",
        "-DQT_CORE_LIB",
        "-DQT_GUI_LIB",
        "-DQT_NEEDS_QMAIN",
        "-DQT_NETWORK_LIB",
        "-DQT_WIDGETS_LIB",
        "-DUNICODE",
        "-DWIN32",
        "-DWIN64",
        "-D_ENABLE_EXTENDED_ALIGNED_STORAGE",
        "-D_UNICODE",
        "-D_WIN64",
        "-DQ_CREATOR_RUN",
        "-I",
        "D:\\Qt\\Tools\\QtCreator\\share\\qtcreator\\cplusplus\\wrappedMingwHeaders",
        "-I",
        "D:\\Qt\\Tools\\QtCreator\\share\\qtcreator\\cplusplus\\wrappedQtHeaders",
        "-I",
        "D:\\Qt\\Tools\\QtCreator\\share\\qtcreator\\cplusplus\\wrappedQtHeaders\\QtCore",
        "-I",
        "C:\\Users\\103so\\Desktop\\Time Comtrollerr\\build-Client-Desktop_Qt_6_3_1_MinGW_64_bit-Debug",
        "-I",
        "C:\\Users\\103so\\Desktop\\Time Comtrollerr\\Client",
        "-I",
        "C:\\Users\\103so\\Desktop\\Time Comtrollerr\\build-Client-Desktop_Qt_6_3_1_MinGW_64_bit-Debug\\Client_autogen\\include",
        "-I",
        "D:\\Qt\\6.3.1\\mingw_64\\include\\QtCore",
        "-I",
        "D:\\Qt\\6.3.1\\mingw_64\\include",
        "-I",
        "D:\\Qt\\6.3.1\\mingw_64\\mkspecs\\win32-g++",
        "-I",
        "D:\\Qt\\6.3.1\\mingw_64\\include\\QtWidgets",
        "-I",
        "D:\\Qt\\6.3.1\\mingw_64\\include\\QtGui",
        "-I",
        "D:\\Qt\\6.3.1\\mingw_64\\include\\QtNetwork",
        "-isystem",
        "D:\\Qt\\Tools\\mingw1120_64\\lib\\gcc\\x86_64-w64-mingw32\\11.2.0\\include\\c++",
        "-isystem",
        "D:\\Qt\\Tools\\mingw1120_64\\lib\\gcc\\x86_64-w64-mingw32\\11.2.0\\include\\c++\\x86_64-w64-mingw32",
        "-isystem",
        "D:\\Qt\\Tools\\mingw1120_64\\lib\\gcc\\x86_64-w64-mingw32\\11.2.0\\include\\c++\\backward",
        "-isystem",
        "D:\\Qt\\Tools\\QtCreator\\bin\\clang\\lib\\clang\\14.0.3\\include",
        "-isystem",
        "D:\\Qt\\Tools\\mingw1120_64\\x86_64-w64-mingw32\\include",
        "-fmessage-length=0",
        "-fdiagnostics-show-note-include-stack",
        "-fretain-comments-from-system-headers",
        "-fmacro-backtrace-limit=0",
        "-ferror-limit=1000",
        "-x",
        "c++-header",
        "C:\\Users\\103so\\Desktop\\Time Comtrollerr\\Client\\client.h"
    ],
    "directory": "C:/Users/103so/Desktop/Time Comtrollerr/build-Client-Desktop_Qt_6_3_1_MinGW_64_bit-Debug/.qtc_clangd",
    "file": "C:/Users/103so/Desktop/Time Comtrollerr/Client/client.h"
},
{
    "arguments": [
        "clang",
        "-Wno-documentation-unknown-command",
        "-Wno-unknown-warning-option",
        "-Wno-unknown-pragmas",
        "-nostdinc",
        "-nostdinc++",
        "-DQT_QML_DEBUG",
        "-g",
        "-std=gnu++17",
        "-fsyntax-only",
        "-m64",
        "--target=x86_64-w64-mingw32",
        "-DMINGW_HAS_SECURE_API",
        "-DQT_CORE_LIB",
        "-DQT_GUI_LIB",
        "-DQT_NEEDS_QMAIN",
        "-DQT_NETWORK_LIB",
        "-DQT_WIDGETS_LIB",
        "-DUNICODE",
        "-DWIN32",
        "-DWIN64",
        "-D_ENABLE_EXTENDED_ALIGNED_STORAGE",
        "-D_UNICODE",
        "-D_WIN64",
        "-DQ_CREATOR_RUN",
        "-I",
        "D:\\Qt\\Tools\\QtCreator\\share\\qtcreator\\cplusplus\\wrappedMingwHeaders",
        "-I",
        "D:\\Qt\\Tools\\QtCreator\\share\\qtcreator\\cplusplus\\wrappedQtHeaders",
        "-I",
        "D:\\Qt\\Tools\\QtCreator\\share\\qtcreator\\cplusplus\\wrappedQtHeaders\\QtCore",
        "-I",
        "C:\\Users\\103so\\Desktop\\Time Comtrollerr\\build-Client-Desktop_Qt_6_3_1_MinGW_64_bit-Debug",
        "-I",
        "C:\\Users\\103so\\Desktop\\Time Comtrollerr\\Client",
        "-I",
        "C:\\Users\\103so\\Desktop\\Time Comtrollerr\\build-Client-Desktop_Qt_6_3_1_MinGW_64_bit-Debug\\Client_autogen\\include",
        "-I",
        "D:\\Qt\\6.3.1\\mingw_64\\include\\QtCore",
        "-I",
        "D:\\Qt\\6.3.1\\mingw_64\\include",
        "-I",
        "D:\\Qt\\6.3.1\\mingw_64\\mkspecs\\win32-g++",
        "-I",
        "D:\\Qt\\6.3.1\\mingw_64\\include\\QtWidgets",
        "-I",
        "D:\\Qt\\6.3.1\\mingw_64\\include\\QtGui",
        "-I",
        "D:\\Qt\\6.3.1\\mingw_64\\include\\QtNetwork",
        "-isystem",
        "D:\\Qt\\Tools\\mingw1120_64\\lib\\gcc\\x86_64-w64-mingw32\\11.2.0\\include\\c++",
        "-isystem",
        "D:\\Qt\\Tools\\mingw1120_64\\lib\\gcc\\x86_64-w64-mingw32\\11.2.0\\include\\c++\\x86_64-w64-mingw32",
        "-isystem",
        "D:\\Qt\\Tools\\mingw1120_64\\lib\\gcc\\x86_64-w64-mingw32\\11.2.0\\include\\c++\\backward",
        "-isystem",
        "D:\\Qt\\Tools\\QtCreator\\bin\\clang\\lib\\clang\\14.0.3\\include",
        "-isystem",
        "D:\\Qt\\Tools\\mingw1120_64\\x86_64-w64-mingw32\\include",
        "-fmessage-length=0",
        "-fdiagnostics-show-note-include-stack",
        "-fretain-comments-from-system-headers",
        "-fmacro-backtrace-limit=0",
        "-ferror-limit=1000",
        "-x",
        "c++-header",
        "C:\\Users\\103so\\Desktop\\Time Comtrollerr\\Client\\operatingsystemfactory.h"
    ],
    "directory": "C:/Users/103so/Desktop/Time Comtrollerr/build-Client-Desktop_Qt_6_3_1_MinGW_64_bit-Debug/.qtc_clangd",
    "file": "C:/Users/103so/Desktop/Time Comtrollerr/Client/operatingsystemfactory.h"
},
{
    "arguments": [
        "clang",
        "-Wno-documentation-unknown-command",
        "-Wno-unknown-warning-option",
        "-Wno-unknown-pragmas",
        "-nostdinc",
        "-nostdinc++",
        "-DQT_QML_DEBUG",
        "-g",
        "-std=gnu++17",
        "-fsyntax-only",
        "-m64",
        "--target=x86_64-w64-mingw32",
        "-DMINGW_HAS_SECURE_API",
        "-DQT_CORE_LIB",
        "-DQT_GUI_LIB",
        "-DQT_NEEDS_QMAIN",
        "-DQT_NETWORK_LIB",
        "-DQT_WIDGETS_LIB",
        "-DUNICODE",
        "-DWIN32",
        "-DWIN64",
        "-D_ENABLE_EXTENDED_ALIGNED_STORAGE",
        "-D_UNICODE",
        "-D_WIN64",
        "-DQ_CREATOR_RUN",
        "-I",
        "D:\\Qt\\Tools\\QtCreator\\share\\qtcreator\\cplusplus\\wrappedMingwHeaders",
        "-I",
        "D:\\Qt\\Tools\\QtCreator\\share\\qtcreator\\cplusplus\\wrappedQtHeaders",
        "-I",
        "D:\\Qt\\Tools\\QtCreator\\share\\qtcreator\\cplusplus\\wrappedQtHeaders\\QtCore",
        "-I",
        "C:\\Users\\103so\\Desktop\\Time Comtrollerr\\build-Client-Desktop_Qt_6_3_1_MinGW_64_bit-Debug",
        "-I",
        "C:\\Users\\103so\\Desktop\\Time Comtrollerr\\Client",
        "-I",
        "C:\\Users\\103so\\Desktop\\Time Comtrollerr\\build-Client-Desktop_Qt_6_3_1_MinGW_64_bit-Debug\\Client_autogen\\include",
        "-I",
        "D:\\Qt\\6.3.1\\mingw_64\\include\\QtCore",
        "-I",
        "D:\\Qt\\6.3.1\\mingw_64\\include",
        "-I",
        "D:\\Qt\\6.3.1\\mingw_64\\mkspecs\\win32-g++",
        "-I",
        "D:\\Qt\\6.3.1\\mingw_64\\include\\QtWidgets",
        "-I",
        "D:\\Qt\\6.3.1\\mingw_64\\include\\QtGui",
        "-I",
        "D:\\Qt\\6.3.1\\mingw_64\\include\\QtNetwork",
        "-isystem",
        "D:\\Qt\\Tools\\mingw1120_64\\lib\\gcc\\x86_64-w64-mingw32\\11.2.0\\include\\c++",
        "-isystem",
        "D:\\Qt\\Tools\\mingw1120_64\\lib\\gcc\\x86_64-w64-mingw32\\11.2.0\\include\\c++\\x86_64-w64-mingw32",
        "-isystem",
        "D:\\Qt\\Tools\\mingw1120_64\\lib\\gcc\\x86_64-w64-mingw32\\11.2.0\\include\\c++\\backward",
        "-isystem",
        "D:\\Qt\\Tools\\QtCreator\\bin\\clang\\lib\\clang\\14.0.3\\include",
        "-isystem",
        "D:\\Qt\\Tools\\mingw1120_64\\x86_64-w64-mingw32\\include",
        "-fmessage-length=0",
        "-fdiagnostics-show-note-include-stack",
        "-fretain-comments-from-system-headers",
        "-fmacro-backtrace-limit=0",
        "-ferror-limit=1000",
        "-x",
        "c++-header",
        "C:\\Users\\103so\\Desktop\\Time Comtrollerr\\Client\\windowssystem.h"
    ],
    "directory": "C:/Users/103so/Desktop/Time Comtrollerr/build-Client-Desktop_Qt_6_3_1_MinGW_64_bit-Debug/.qtc_clangd",
    "file": "C:/Users/103so/Desktop/Time Comtrollerr/Client/windowssystem.h"
},
{
    "arguments": [
        "clang",
        "-Wno-documentation-unknown-command",
        "-Wno-unknown-warning-option",
        "-Wno-unknown-pragmas",
        "-nostdinc",
        "-nostdinc++",
        "-DQT_QML_DEBUG",
        "-g",
        "-std=gnu++17",
        "-fsyntax-only",
        "-m64",
        "--target=x86_64-w64-mingw32",
        "-DMINGW_HAS_SECURE_API",
        "-DQT_CORE_LIB",
        "-DQT_GUI_LIB",
        "-DQT_NEEDS_QMAIN",
        "-DQT_NETWORK_LIB",
        "-DQT_WIDGETS_LIB",
        "-DUNICODE",
        "-DWIN32",
        "-DWIN64",
        "-D_ENABLE_EXTENDED_ALIGNED_STORAGE",
        "-D_UNICODE",
        "-D_WIN64",
        "-DQ_CREATOR_RUN",
        "-I",
        "D:\\Qt\\Tools\\QtCreator\\share\\qtcreator\\cplusplus\\wrappedMingwHeaders",
        "-I",
        "D:\\Qt\\Tools\\QtCreator\\share\\qtcreator\\cplusplus\\wrappedQtHeaders",
        "-I",
        "D:\\Qt\\Tools\\QtCreator\\share\\qtcreator\\cplusplus\\wrappedQtHeaders\\QtCore",
        "-I",
        "C:\\Users\\103so\\Desktop\\Time Comtrollerr\\build-Client-Desktop_Qt_6_3_1_MinGW_64_bit-Debug",
        "-I",
        "C:\\Users\\103so\\Desktop\\Time Comtrollerr\\Client",
        "-I",
        "C:\\Users\\103so\\Desktop\\Time Comtrollerr\\build-Client-Desktop_Qt_6_3_1_MinGW_64_bit-Debug\\Client_autogen\\include",
        "-I",
        "D:\\Qt\\6.3.1\\mingw_64\\include\\QtCore",
        "-I",
        "D:\\Qt\\6.3.1\\mingw_64\\include",
        "-I",
        "D:\\Qt\\6.3.1\\mingw_64\\mkspecs\\win32-g++",
        "-I",
        "D:\\Qt\\6.3.1\\mingw_64\\include\\QtWidgets",
        "-I",
        "D:\\Qt\\6.3.1\\mingw_64\\include\\QtGui",
        "-I",
        "D:\\Qt\\6.3.1\\mingw_64\\include\\QtNetwork",
        "-isystem",
        "D:\\Qt\\Tools\\mingw1120_64\\lib\\gcc\\x86_64-w64-mingw32\\11.2.0\\include\\c++",
        "-isystem",
        "D:\\Qt\\Tools\\mingw1120_64\\lib\\gcc\\x86_64-w64-mingw32\\11.2.0\\include\\c++\\x86_64-w64-mingw32",
        "-isystem",
        "D:\\Qt\\Tools\\mingw1120_64\\lib\\gcc\\x86_64-w64-mingw32\\11.2.0\\include\\c++\\backward",
        "-isystem",
        "D:\\Qt\\Tools\\QtCreator\\bin\\clang\\lib\\clang\\14.0.3\\include",
        "-isystem",
        "D:\\Qt\\Tools\\mingw1120_64\\x86_64-w64-mingw32\\include",
        "-fmessage-length=0",
        "-fdiagnostics-show-note-include-stack",
        "-fretain-comments-from-system-headers",
        "-fmacro-backtrace-limit=0",
        "-ferror-limit=1000",
        "-x",
        "c++-header",
        "C:\\Users\\103so\\Desktop\\Time Comtrollerr\\Client\\operatingsystemprogram.h"
    ],
    "directory": "C:/Users/103so/Desktop/Time Comtrollerr/build-Client-Desktop_Qt_6_3_1_MinGW_64_bit-Debug/.qtc_clangd",
    "file": "C:/Users/103so/Desktop/Time Comtrollerr/Client/operatingsystemprogram.h"
},
{
    "arguments": [
        "clang",
        "-Wno-documentation-unknown-command",
        "-Wno-unknown-warning-option",
        "-Wno-unknown-pragmas",
        "-nostdinc",
        "-nostdinc++",
        "-DQT_QML_DEBUG",
        "-g",
        "-std=gnu++17",
        "-fsyntax-only",
        "-m64",
        "--target=x86_64-w64-mingw32",
        "-DMINGW_HAS_SECURE_API",
        "-DQT_CORE_LIB",
        "-DQT_GUI_LIB",
        "-DQT_NEEDS_QMAIN",
        "-DQT_NETWORK_LIB",
        "-DQT_WIDGETS_LIB",
        "-DUNICODE",
        "-DWIN32",
        "-DWIN64",
        "-D_ENABLE_EXTENDED_ALIGNED_STORAGE",
        "-D_UNICODE",
        "-D_WIN64",
        "-DQ_CREATOR_RUN",
        "-I",
        "D:\\Qt\\Tools\\QtCreator\\share\\qtcreator\\cplusplus\\wrappedMingwHeaders",
        "-I",
        "D:\\Qt\\Tools\\QtCreator\\share\\qtcreator\\cplusplus\\wrappedQtHeaders",
        "-I",
        "D:\\Qt\\Tools\\QtCreator\\share\\qtcreator\\cplusplus\\wrappedQtHeaders\\QtCore",
        "-I",
        "C:\\Users\\103so\\Desktop\\Time Comtrollerr\\build-Client-Desktop_Qt_6_3_1_MinGW_64_bit-Debug",
        "-I",
        "C:\\Users\\103so\\Desktop\\Time Comtrollerr\\Client",
        "-I",
        "C:\\Users\\103so\\Desktop\\Time Comtrollerr\\build-Client-Desktop_Qt_6_3_1_MinGW_64_bit-Debug\\Client_autogen\\include",
        "-I",
        "D:\\Qt\\6.3.1\\mingw_64\\include\\QtCore",
        "-I",
        "D:\\Qt\\6.3.1\\mingw_64\\include",
        "-I",
        "D:\\Qt\\6.3.1\\mingw_64\\mkspecs\\win32-g++",
        "-I",
        "D:\\Qt\\6.3.1\\mingw_64\\include\\QtWidgets",
        "-I",
        "D:\\Qt\\6.3.1\\mingw_64\\include\\QtGui",
        "-I",
        "D:\\Qt\\6.3.1\\mingw_64\\include\\QtNetwork",
        "-isystem",
        "D:\\Qt\\Tools\\mingw1120_64\\lib\\gcc\\x86_64-w64-mingw32\\11.2.0\\include\\c++",
        "-isystem",
        "D:\\Qt\\Tools\\mingw1120_64\\lib\\gcc\\x86_64-w64-mingw32\\11.2.0\\include\\c++\\x86_64-w64-mingw32",
        "-isystem",
        "D:\\Qt\\Tools\\mingw1120_64\\lib\\gcc\\x86_64-w64-mingw32\\11.2.0\\include\\c++\\backward",
        "-isystem",
        "D:\\Qt\\Tools\\QtCreator\\bin\\clang\\lib\\clang\\14.0.3\\include",
        "-isystem",
        "D:\\Qt\\Tools\\mingw1120_64\\x86_64-w64-mingw32\\include",
        "-fmessage-length=0",
        "-fdiagnostics-show-note-include-stack",
        "-fretain-comments-from-system-headers",
        "-fmacro-backtrace-limit=0",
        "-ferror-limit=1000",
        "-x",
        "c++-header",
        "C:\\Users\\103so\\Desktop\\Time Comtrollerr\\Client\\windowssystemprogram.h"
    ],
    "directory": "C:/Users/103so/Desktop/Time Comtrollerr/build-Client-Desktop_Qt_6_3_1_MinGW_64_bit-Debug/.qtc_clangd",
    "file": "C:/Users/103so/Desktop/Time Comtrollerr/Client/windowssystemprogram.h"
},
{
    "arguments": [
        "clang",
        "-Wno-documentation-unknown-command",
        "-Wno-unknown-warning-option",
        "-Wno-unknown-pragmas",
        "-nostdinc",
        "-nostdinc++",
        "-DQT_QML_DEBUG",
        "-g",
        "-std=gnu++17",
        "-fsyntax-only",
        "-m64",
        "--target=x86_64-w64-mingw32",
        "-DMINGW_HAS_SECURE_API",
        "-DQT_CORE_LIB",
        "-DQT_GUI_LIB",
        "-DQT_NEEDS_QMAIN",
        "-DQT_NETWORK_LIB",
        "-DQT_WIDGETS_LIB",
        "-DUNICODE",
        "-DWIN32",
        "-DWIN64",
        "-D_ENABLE_EXTENDED_ALIGNED_STORAGE",
        "-D_UNICODE",
        "-D_WIN64",
        "-DQ_CREATOR_RUN",
        "-I",
        "D:\\Qt\\Tools\\QtCreator\\share\\qtcreator\\cplusplus\\wrappedMingwHeaders",
        "-I",
        "D:\\Qt\\Tools\\QtCreator\\share\\qtcreator\\cplusplus\\wrappedQtHeaders",
        "-I",
        "D:\\Qt\\Tools\\QtCreator\\share\\qtcreator\\cplusplus\\wrappedQtHeaders\\QtCore",
        "-I",
        "C:\\Users\\103so\\Desktop\\Time Comtrollerr\\build-Client-Desktop_Qt_6_3_1_MinGW_64_bit-Debug",
        "-I",
        "C:\\Users\\103so\\Desktop\\Time Comtrollerr\\Client",
        "-I",
        "C:\\Users\\103so\\Desktop\\Time Comtrollerr\\build-Client-Desktop_Qt_6_3_1_MinGW_64_bit-Debug\\Client_autogen\\include",
        "-I",
        "D:\\Qt\\6.3.1\\mingw_64\\include\\QtCore",
        "-I",
        "D:\\Qt\\6.3.1\\mingw_64\\include",
        "-I",
        "D:\\Qt\\6.3.1\\mingw_64\\mkspecs\\win32-g++",
        "-I",
        "D:\\Qt\\6.3.1\\mingw_64\\include\\QtWidgets",
        "-I",
        "D:\\Qt\\6.3.1\\mingw_64\\include\\QtGui",
        "-I",
        "D:\\Qt\\6.3.1\\mingw_64\\include\\QtNetwork",
        "-isystem",
        "D:\\Qt\\Tools\\mingw1120_64\\lib\\gcc\\x86_64-w64-mingw32\\11.2.0\\include\\c++",
        "-isystem",
        "D:\\Qt\\Tools\\mingw1120_64\\lib\\gcc\\x86_64-w64-mingw32\\11.2.0\\include\\c++\\x86_64-w64-mingw32",
        "-isystem",
        "D:\\Qt\\Tools\\mingw1120_64\\lib\\gcc\\x86_64-w64-mingw32\\11.2.0\\include\\c++\\backward",
        "-isystem",
        "D:\\Qt\\Tools\\QtCreator\\bin\\clang\\lib\\clang\\14.0.3\\include",
        "-isystem",
        "D:\\Qt\\Tools\\mingw1120_64\\x86_64-w64-mingw32\\include",
        "-fmessage-length=0",
        "-fdiagnostics-show-note-include-stack",
        "-fretain-comments-from-system-headers",
        "-fmacro-backtrace-limit=0",
        "-ferror-limit=1000",
        "-x",
        "c++-header",
        "C:\\Users\\103so\\Desktop\\Time Comtrollerr\\Client\\activitytime.h"
    ],
    "directory": "C:/Users/103so/Desktop/Time Comtrollerr/build-Client-Desktop_Qt_6_3_1_MinGW_64_bit-Debug/.qtc_clangd",
    "file": "C:/Users/103so/Desktop/Time Comtrollerr/Client/activitytime.h"
},
{
    "arguments": [
        "clang",
        "-Wno-documentation-unknown-command",
        "-Wno-unknown-warning-option",
        "-Wno-unknown-pragmas",
        "-nostdinc",
        "-nostdinc++",
        "-DQT_QML_DEBUG",
        "-g",
        "-std=gnu++17",
        "-fsyntax-only",
        "-m64",
        "--target=x86_64-w64-mingw32",
        "-DMINGW_HAS_SECURE_API",
        "-DQT_CORE_LIB",
        "-DQT_GUI_LIB",
        "-DQT_NEEDS_QMAIN",
        "-DQT_NETWORK_LIB",
        "-DQT_WIDGETS_LIB",
        "-DUNICODE",
        "-DWIN32",
        "-DWIN64",
        "-D_ENABLE_EXTENDED_ALIGNED_STORAGE",
        "-D_UNICODE",
        "-D_WIN64",
        "-DQ_CREATOR_RUN",
        "-I",
        "D:\\Qt\\Tools\\QtCreator\\share\\qtcreator\\cplusplus\\wrappedMingwHeaders",
        "-I",
        "D:\\Qt\\Tools\\QtCreator\\share\\qtcreator\\cplusplus\\wrappedQtHeaders",
        "-I",
        "D:\\Qt\\Tools\\QtCreator\\share\\qtcreator\\cplusplus\\wrappedQtHeaders\\QtCore",
        "-I",
        "C:\\Users\\103so\\Desktop\\Time Comtrollerr\\build-Client-Desktop_Qt_6_3_1_MinGW_64_bit-Debug",
        "-I",
        "C:\\Users\\103so\\Desktop\\Time Comtrollerr\\Client",
        "-I",
        "C:\\Users\\103so\\Desktop\\Time Comtrollerr\\build-Client-Desktop_Qt_6_3_1_MinGW_64_bit-Debug\\Client_autogen\\include",
        "-I",
        "D:\\Qt\\6.3.1\\mingw_64\\include\\QtCore",
        "-I",
        "D:\\Qt\\6.3.1\\mingw_64\\include",
        "-I",
        "D:\\Qt\\6.3.1\\mingw_64\\mkspecs\\win32-g++",
        "-I",
        "D:\\Qt\\6.3.1\\mingw_64\\include\\QtWidgets",
        "-I",
        "D:\\Qt\\6.3.1\\mingw_64\\include\\QtGui",
        "-I",
        "D:\\Qt\\6.3.1\\mingw_64\\include\\QtNetwork",
        "-isystem",
        "D:\\Qt\\Tools\\mingw1120_64\\lib\\gcc\\x86_64-w64-mingw32\\11.2.0\\include\\c++",
        "-isystem",
        "D:\\Qt\\Tools\\mingw1120_64\\lib\\gcc\\x86_64-w64-mingw32\\11.2.0\\include\\c++\\x86_64-w64-mingw32",
        "-isystem",
        "D:\\Qt\\Tools\\mingw1120_64\\lib\\gcc\\x86_64-w64-mingw32\\11.2.0\\include\\c++\\backward",
        "-isystem",
        "D:\\Qt\\Tools\\QtCreator\\bin\\clang\\lib\\clang\\14.0.3\\include",
        "-isystem",
        "D:\\Qt\\Tools\\mingw1120_64\\x86_64-w64-mingw32\\include",
        "-fmessage-length=0",
        "-fdiagnostics-show-note-include-stack",
        "-fretain-comments-from-system-headers",
        "-fmacro-backtrace-limit=0",
        "-ferror-limit=1000",
        "-x",
        "c++-header",
        "C:\\Users\\103so\\Desktop\\Time Comtrollerr\\Client\\app.h"
    ],
    "directory": "C:/Users/103so/Desktop/Time Comtrollerr/build-Client-Desktop_Qt_6_3_1_MinGW_64_bit-Debug/.qtc_clangd",
    "file": "C:/Users/103so/Desktop/Time Comtrollerr/Client/app.h"
}
]